bota_payload_utils/__init__.py
bota_payload_utils/bota_payload_utils_ext.pyd
bota_payload_utils/BotaPayloadCompensator.dll
bota_payload_utils/BotaPayloadEstimator.dll
bota_payload_utils/hardware_interfaces.py
bota_payload_utils-0.0.2.dist-info/METADATA
bota_payload_utils-0.0.2.dist-info/WHEEL
bota_payload_utils-0.0.2.dist-info/RECORD
