Metadata-Version: 2.1
Name: bota-payload-utils
Version: 0.0.2
Summary: Python binding for the Bota Payload Utils C++ library
Author-Email: Raul Cruz-Oliver <support@botasys.com>
Classifier: License :: OSI Approved :: BSD License
Project-URL: Homepage, https://botasys.com
Requires-Python: >=3.8
